{
    "fluentMethods": true,
    "relationships": [
        {
            "relationshipType": "many-to-many",
            "otherEntityRelationshipName": "product",
            "relationshipName": "user",
            "otherEntityName": "user",
            "otherEntityField": "id",
            "ownerSide": true
        }
    ],
    "fields": [
        {
            "fieldName": "name",
            "fieldType": "String",
            "fieldValidateRules": [
                "required",
                "maxlength"
            ],
            "fieldValidateRulesMaxlength": 75
        }
    ],
    "changelogDate": "20180421154424",
    "entityTableName": "product",
    "dto": "mapstruct",
    "pagination": "infinite-scroll",
    "service": "serviceClass",
    "jpaMetamodelFiltering": false
}